seqhash/__init__.py
seqhash-1.0.0.dist-info/LICENSE
seqhash-1.0.0.dist-info/METADATA
seqhash-1.0.0.dist-info/WHEEL
seqhash-1.0.0.dist-info/top_level.txt
seqhash-1.0.0.dist-info/RECORD
